itsybitsy/__init__.py
itsybitsy/url_normalize.py
itsybitsy/util.py
itsybitsy/spider/__init__.py
itsybitsy/spider/asynchronous.py
itsybitsy/spider/multithreaded.py
itsybitsy-0.2.dist-info/LICENSE
itsybitsy-0.2.dist-info/METADATA
itsybitsy-0.2.dist-info/WHEEL
itsybitsy-0.2.dist-info/top_level.txt
itsybitsy-0.2.dist-info/RECORD
